{
  "labels": [
    {
      "on": "FLEX On",
      "off": "FLEX On"
    },
    {
      "on": "FLEX PTT",
      "off": "FLEX PTT"
    },
    {
      "on": "FLEX Factory Reset Off",
      "off": "FLEX Factory Reset Off"
    },
    {
      "on": "FLEX Factory Reset On",
      "off": "FLEX Factory Reset On"
    },
    {
      "on": "FLEX DC Power",
      "off": "FLEX DC Power"
    },
    {
      "on": "Relay 6 On",
      "off": "Relay 6 Off"
    },
    {
      "on": "Relay 7 On",
      "off": "Relay 7 Off"
    },
    {
      "on": "Relay 8 On",
      "off": "Relay 8 Off"
    }
  ],
  "relayCount": 8,
  "title": "FLEX Control"
}